metacontroller/__init__.py
metacontroller/metacontroller.py
metacontroller/metacontroller_with_binary_mapper.py
metacontroller/transformer_with_resnet.py
metacontroller_pytorch-0.0.42.dist-info/METADATA
metacontroller_pytorch-0.0.42.dist-info/WHEEL
metacontroller_pytorch-0.0.42.dist-info/licenses/LICENSE
metacontroller_pytorch-0.0.42.dist-info/RECORD
