Metadata-Version: 2.4
Name: metacontroller-pytorch
Version: 0.0.42
Summary: Transformer Metacontroller
Project-URL: Homepage, https://pypi.org/project/metacontroller/
Project-URL: Repository, https://github.com/lucidrains/metacontroller
Author-email: Phil Wang <lucidrains@gmail.com>
License: MIT License
License-File: LICENSE
Keywords: artificial intelligence,deep learning,hierarchical reinforcement learning,latent steering
Classifier: Development Status :: 4 - Beta
Classifier: Intended Audience :: Developers
Classifier: License :: OSI Approved :: MIT License
Classifier: Programming Language :: Python :: 3.9
Classifier: Topic :: Scientific/Engineering :: Artificial Intelligence
Requires-Python: >=3.9
Requires-Dist: assoc-scan>=0.0.3
Requires-Dist: discrete-continuous-embed-readout>=0.1.12
Requires-Dist: einops>=0.8.1
Requires-Dist: einx>=0.3.0
Requires-Dist: loguru
Requires-Dist: memmap-replay-buffer>=0.0.25
Requires-Dist: torch-einops-utils>=0.0.19
Requires-Dist: torch>=2.5
Requires-Dist: vector-quantize-pytorch>=1.27.20
Requires-Dist: x-evolution>=0.1.23
Requires-Dist: x-mlps-pytorch
Requires-Dist: x-transformers
Provides-Extra: examples
Provides-Extra: test
Requires-Dist: pytest; extra == 'test'
